#### 实例一：简单使用

##### 构造

```
public enum Wife_0 {
    Shi,
    Di,
    Xin
}
```

##### 反编译：

```assembly
public final class data_struction._enum.Wife_0 extends java.lang.Enum<data_struction._enum.Wife_0> {
  public static final data_struction._enum.Wife_0 Shi;

  public static final data_struction._enum.Wife_0 Xin;

  public static data_struction._enum.Wife_0[] values();
    Code:
       0: getstatic     #1                  // Field $VALUES:[Ldata_struction/_enum/Wife_0;
       3: invokevirtual #2                  // Method "[Ldata_struction/_enum/Wife_0;".clone:()Ljava/lang/Object;
       6: checkcast     #3                  // class "[Ldata_struction/_enum/Wife_0;"
       9: areturn

  public static data_struction._enum.Wife_0 valueOf(java.lang.String);
    Code:
       0: ldc           #4                  // class data_struction/_enum/Wife_0
       2: aload_0
       3: invokestatic  #5                  // Method java/lang/Enum.valueOf:(Ljava/lang/Class;Ljava/lang/String;)Ljava/lang/Enum;
       6: checkcast     #4                  // class data_struction/_enum/Wife_0
       9: areturn

  static {};
    Code:
       0: new           #4                  // class data_struction/_enum/Wife_0
       3: dup
       4: ldc           #7                  // String Shi
       6: iconst_0
       7: invokespecial #8                  // Method "<init>":(Ljava/lang/String;I)V
      10: putstatic     #9                  // Field Shi:Ldata_struction/_enum/Wife_0;
      13: new           #4                  // class data_struction/_enum/Wife_0
      16: dup
      17: ldc           #10                 // String Xin
      19: iconst_1
      20: invokespecial #8                  // Method "<init>":(Ljava/lang/String;I)V
      23: putstatic     #11                 // Field Xin:Ldata_struction/_enum/Wife_0;
      26: iconst_2
      27: anewarray     #4                  // class data_struction/_enum/Wife_0
      30: dup
      31: iconst_0
      32: getstatic     #9                  // Field Shi:Ldata_struction/_enum/Wife_0;
      35: aastore
      36: dup
      37: iconst_1
      38: getstatic     #11                 // Field Xin:Ldata_struction/_enum/Wife_0;
      41: aastore
      42: putstatic     #1                  // Field $VALUES:[Ldata_struction/_enum/Wife_0;
      45: return
}
```

通过反编译，可以看出通过 static 静态域创建了 两个 Wife_0 对象；



##### 使用

其中 values() 函数返回 Wife_0[]

```java
System.out.println(Arrays.toString(Wife_0.values())); // [Shi, Xin]
System.out.println(Wife_0.Shi);						  // Shi
System.out.println(Wife_0.Shi.getClass());			  // class data_struction._enum.Wife_0
System.out.println(Wife_0.valueOf("Shi").getClass()); // class data_struction._enum.Wife_0
```



#### 实例二：面向对象

```java
public enum Wife {
    Shi("石原里美"),
    Di("迪丽热巴"),
    Xin("新垣结衣");

    private final String name;
    private Wife(String name) {
        this.name = name;
    }

    public String getName() {
        return name;
    }
}
System.out.println(Wife_1.values().getClass()); 	    // values() 返回 Wife_1[]
System.out.println(Arrays.toString(Wife_1.values()));   // [Shi, Di, Xin]
System.out.println(Wife_1.valueOf("Shi").getClass());   // class data_struction._enum.Wife_1
System.out.println(Wife_1.valueOf("Shi").getName());    // 石原里美
```



#### 实例三：实现接口

```java
interface Talking {
    void say();
}

public enum Wife_2 implements Talking{
    Shi("石原里美"),
    Xin("新垣结衣");

    private String name;

    private Wife_2(String name) {
        this.name = name;
    }

    @Override
    public void say() {
        System.out.println("I'm " + name);
    }

    public static void main(String[] args) {
        Wife_2 shi = Wife_2.Shi;
        System.out.println(shi.getClass());                       // class data_struction._enum.Wife_2
        System.out.println(shi);								  // Shi
        System.out.println(Arrays.toString(Wife_2.values()));     // [Shi, Xin]
        shi.say();												  // I'm 石原里美
    }
}
```













